MANIFEST.in
requirements.txt
setup.py
test-requirements.txt
checkmyws/__init__.py
checkmyws/client.py
checkmyws/exception.py
checkmyws_python.egg-info/PKG-INFO
checkmyws_python.egg-info/SOURCES.txt
checkmyws_python.egg-info/dependency_links.txt
checkmyws_python.egg-info/requires.txt
checkmyws_python.egg-info/top_level.txt