Metadata-Version: 1.1
Name: checkmyws-python
Version: 0.1.8
Summary: Check my Website client
Home-page: https://github.com/checkmyws/checkmyws-python
Author: Check my Website Team
Author-email: contact@checkmy.ws
License: MIT License
Platform: UNKNOWN
Classifier: Development Status :: 3 - Alpha
Classifier: Intended Audience :: Developers
Classifier: License :: OSI Approved :: MIT License
Classifier: Programming Language :: Python
Classifier: Programming Language :: Python :: 2.7
Classifier: Programming Language :: Python :: 3
